isocrypt/__init__.py
isocrypt/libcryptsetup.py
isocrypt/main.py
isocrypt-0.1.4.dist-info/METADATA
isocrypt-0.1.4.dist-info/WHEEL
isocrypt-0.1.4.dist-info/entry_points.txt
isocrypt-0.1.4.dist-info/RECORD
