Metadata-Version: 2.1
Name: isocrypt
Version: 0.1.4
Summary: 
Author: Poe Rhiza
Author-email: poerhiz@gmail.com
Requires-Python: >=3.8,<4.0
Classifier: Operating System :: POSIX :: Linux
Classifier: Programming Language :: Python :: 3
Classifier: Programming Language :: Python :: 3.8
Classifier: Programming Language :: Python :: 3.9
Classifier: Programming Language :: Python :: 3.10
Classifier: Programming Language :: Python :: 3.11
Classifier: Programming Language :: Python :: 3.12
Classifier: Programming Language :: Python :: 3.13
Requires-Dist: humanfriendly (>=10.0,<11.0)
Requires-Dist: typer (>=0.4.0,<0.5.0)
